Metadata-Version: 2.1
Name: Python-Mango-Office-API
Version: 3.7.4
Summary: API wrapper for Mango Office.
Home-page: https://github.com/dasshit/Python-Mango-Office-API
Author: dasshit
Author-email: v.korobov@mangotele.com
License: GPL2
Keywords: mangooffice mango
Platform: UNKNOWN
Classifier: Development Status :: 5 - Production/Stable
Classifier: Programming Language :: Python :: 3
Classifier: Environment :: Console
Classifier: License :: OSI Approved :: GNU General Public License v2 (GPLv2)
